Metadata-Version: 2.1
Name: stm-gnn
Version: 1.0.0
Summary: STM-Graph: A Python Framework for Spatio-Temporal Mapping and Graph Neural Network Predictions
Author-email: Amirhossein Ghaffari <amirhossein.ghaffari@oulu.fi>
License: MIT
Project-URL: Repository, https://github.com/Ahghaffari/stm_graph
Project-URL: Bug Tracker, https://github.com/Ahghaffari/stm_graph/issues
Keywords: spatial-temporal,graph neural networks,mapping,torch geometric temporal,framework
Classifier: Development Status :: 4 - Beta
Classifier: Intended Audience :: Science/Research
Classifier: Programming Language :: Python :: 3
Classifier: Operating System :: OS Independent
Classifier: License :: OSI Approved :: MIT License
Requires-Python: <3.9,>=3.8
License-File: LICENSE
Requires-Dist: contextily>=1.5.2
Requires-Dist: geopandas>=0.13.2
Requires-Dist: matplotlib>=3.7.5
Requires-Dist: networkx>=3.1
Requires-Dist: numpy>=1.24.4
Requires-Dist: osmnx==1.9.4
Requires-Dist: pandas>=1.3.5
Requires-Dist: pyproj>=3.5.0
Requires-Dist: scikit-learn>=1.3.2
Requires-Dist: scipy>=1.10.1
Requires-Dist: Shapely>=2.0.6
Requires-Dist: tqdm>=4.66.5
Requires-Dist: wandb==0.19.1
Provides-Extra: torch-extensions
Requires-Dist: torch-scatter>=2.1.2; extra == "torch-extensions"
Requires-Dist: torch-sparse>=0.6.18; extra == "torch-extensions"
Requires-Dist: torch-cluster>=1.6.3; extra == "torch-extensions"
Requires-Dist: torch-spline-conv>=1.2.2; extra == "torch-extensions"
Requires-Dist: torch-geometric==2.4.0; extra == "torch-extensions"
Requires-Dist: torch-geometric-temporal==0.54.0; extra == "torch-extensions"
